async_dns/__init__.py
async_dns/core/__init__.py
async_dns/core/address.py
async_dns/core/cache.py
async_dns/core/config/__init__.py
async_dns/core/config/nt.py
async_dns/core/config/posix.py
async_dns/core/config/root.py
async_dns/core/hosts.py
async_dns/core/logger.py
async_dns/core/nameserver.py
async_dns/core/rand.py
async_dns/core/record.py
async_dns/core/types.py
async_dns/core/utils.py
async_dns/resolver/__init__.py
async_dns/resolver/__main__.py
async_dns/resolver/doh/__init__.py
async_dns/resolver/doh/request.py
async_dns/resolver/query.py
async_dns/resolver/tcp.py
async_dns/resolver/udp.py
async_dns/resolver/util.py
async_dns/server/__init__.py
async_dns/server/__main__.py
async_dns/server/serve.py
async_dns-1.1.10.dist-info/LICENSE
async_dns-1.1.10.dist-info/WHEEL
async_dns-1.1.10.dist-info/METADATA
async_dns-1.1.10.dist-info/RECORD
