Metadata-Version: 2.1
Name: async-dns
Version: 1.1.10
Summary: Asynchronous DNS client and server
Home-page: https://github.com/gera2ld/async_dns
License: MIT
Keywords: async,dns,asyncio
Author: Gerald
Author-email: gera2ld@live.com
Requires-Python: >=3.6,<4.0
Classifier: License :: OSI Approved :: MIT License
Classifier: Programming Language :: Python :: 3
Classifier: Programming Language :: Python :: 3.6
Classifier: Programming Language :: Python :: 3.7
Classifier: Programming Language :: Python :: 3.8
Classifier: Programming Language :: Python :: 3.9
Project-URL: Repository, https://github.com/gera2ld/async_dns
